kge/__init__.py
kge/cli/__init__.py
kge/cli/main.py
kge/completion/__init__.py
kge_kubectl_get_events-0.11.4.dist-info/licenses/LICENSE
kge_kubectl_get_events-0.11.4.dist-info/METADATA
kge_kubectl_get_events-0.11.4.dist-info/WHEEL
kge_kubectl_get_events-0.11.4.dist-info/entry_points.txt
kge_kubectl_get_events-0.11.4.dist-info/top_level.txt
kge_kubectl_get_events-0.11.4.dist-info/RECORD
