Metadata-Version: 2.4
Name: kge-kubectl-get-events
Version: 0.11.4
Summary: Kubernetes utility for viewing pod and failed replicaset events
Author-email: Jesse Goodier <31039225+jessegoodier@users.noreply.github.com>
License: MIT
Project-URL: Homepage, https://github.com/jessegoodier/kge
Project-URL: Repository, https://github.com/jessegoodier/kge
Project-URL: Documentation, https://github.com/jessegoodier/kge/blob/main/README.md
Project-URL: Bug Tracker, https://github.com/jessegoodier/kge/issues
Keywords: kubernetes,troubleshooting,kubectl,events,pod,replicaset,failed,event
Classifier: Development Status :: 4 - Beta
Classifier: Intended Audience :: Developers
Classifier: Programming Language :: Python :: 3
Classifier: Programming Language :: Python :: 3.11
Classifier: Topic :: Software Development :: Libraries :: Python Modules
Classifier: Topic :: System :: Systems Administration
Classifier: Topic :: Utilities
Requires-Python: <4.0,>=3.11
License-File: LICENSE
Requires-Dist: rich<14.0.0,>=13.7.0
Requires-Dist: kubernetes<33.0.0,>=32.0.1
Requires-Dist: prompt_toolkit
Provides-Extra: dev
Requires-Dist: pytest<9.0.0,>=8.0.0; extra == "dev"
Requires-Dist: black; extra == "dev"
Requires-Dist: isort; extra == "dev"
Requires-Dist: mypy; extra == "dev"
Requires-Dist: build; extra == "dev"
Dynamic: license-file
